{
  "keyboard": "4btn",
  "manufacturer": "Custom",
  "maintainer": "knowSkill",
  "url": "",
  "firmware": "qmk",
  "bootloader": "rp2040",
  "processor": "RP2040",
  "matrix_pins": {
      "cols": ["GP6", "GP7", "GP8", "GP9"],
      "rows": ["GP29"]
  },
  "matrix_size": { "rows": 1, "cols": 4 },
  "layouts": {
    "LAYOUT": {
      "layout": [
        { "label": "Key1", "matrix": [0, 0], "x": 0, "y": 0 },
        { "label": "Key2", "matrix": [0, 1], "x": 1, "y": 0 },
        { "label": "Key3", "matrix": [0, 2], "x": 2, "y": 0 },
        { "label": "Key4", "matrix": [0, 3], "x": 3, "y": 0 }
      ]
    }
  }
}